borgback/__init__.py
borgback/backup.py
src/__init__.py
src/backup.py
borgback-1.0.dist-info/LICENSE
borgback-1.0.dist-info/METADATA
borgback-1.0.dist-info/WHEEL
borgback-1.0.dist-info/entry_points.txt
borgback-1.0.dist-info/top_level.txt
borgback-1.0.dist-info/RECORD
