Metadata-Version: 2.1
Name: borgback
Version: 1.0
Summary: Scheduled backups using Borg
Home-page: UNKNOWN
Author: zakora
License: UNKNOWN
Platform: UNKNOWN
Classifier: Development Status :: 5 - Production/Stable
Classifier: Environment :: No Input/Output (Daemon)
Classifier: Intended Audience :: End Users/Desktop
Classifier: Intended Audience :: System Administrators
Classifier: License :: OSI Approved :: Apache Software License
Classifier: Operating System :: POSIX :: Linux
Classifier: Programming Language :: Python :: 3.5
Classifier: Programming Language :: Python :: 3.6
Classifier: Programming Language :: Python :: 3.7
Classifier: Topic :: System :: Archiving :: Backup
Requires-Python: ~=3.5
Requires-Dist: python-dateutil (~=2.7)
Requires-Dist: toml (~=0.9)
Requires-Dist: xdg (~=3.0)
